<?xml version="1.0" encoding="utf-8" ?>
<Table ChipName="hi3516c300" Version="1.0.3.0">
    <Page Name="ExposureAttr">
	    <Group Name="Exposure">
            <Field Name="ByPass">0</Field>
            <Field Name="OpType">0</Field>
            <Field Name="AERunInterval">1</Field>
            <Field Name="HistStatAdjust">1</Field>
		    <Field Name="AERouteExValid">1</Field>
        </Group>
		<Group Name="Exposure Auto">
            <Field Name="ExpTimeMax">104818</Field>
            <Field Name="ExpTimeMin">10</Field>
            <Field Name="AGainMax">15872</Field>
            <Field Name="AGainMin">1024</Field>
            <Field Name="DGainMax">1024</Field>
            <Field Name="DGainMin">1024</Field>
            <Field Name="ISPDGainMax">2048</Field>
            <Field Name="ISPDGainMin">1024</Field>
            <Field Name="SysGainMax">32768</Field>
            <Field Name="SysGainMin">1024</Field>
            <Field Name="GainThreshold">2445495</Field>
            <Field Name="Speed">64</Field>
            <Field Name="Tolerance">2</Field>
            <Field Name="Compensation">64</Field>
            <Field Name="EVBias">1024</Field>
            <Field Name="AEStrategyMode">0</Field>
            <Field Name="HistRatioSlope">144</Field>
            <Field Name="MaxHistOffset">28</Field>
            <Field Name="AEMode">1</Field>
            <Field Name="AntiflickerEnable">0</Field>
            <Field Name="AntiflickerFrequency">50</Field>
            <Field Name="AntiflickerMod">1</Field>
            <Field Name="SubflickerEnable">0</Field>
            <Field Name="SubflickerLumaDiff">50</Field>
            <Field Name="BlackDelayFrame">8</Field>
            <Field Name="WhiteDelayFrame">0</Field>
        </Group>
	    <Group Name="AeRouterEx">
            <Field Name="TotalNum">8</Field>
            <Field Name="RouteEXIntTime">32,20000,40000,40000,50000,50000,83000,83000</Field>
            <Field Name="RouteEXAGain">1024,1024,1024,2048,2048,15872,15872,15872</Field>
            <Field Name="RouteEXDGain">1024,1024,1024,1024,1024,1024,1024,1240</Field>
		    <Field Name="RouteEXISPDGain">1024,1024,1024,1024,1024,1024,1024,1024</Field>
        </Group>
	    <Group Name="AeWeightTab">
            <Field Name="AeWeight">1,1,1,1,1,1,1,1,1,1,1,1,1,1,1,1,1,1,1,1,1,1,1,1,1,1,1,1,1,1,1,1,1,1,1,1,1,1,1,1,1,1,1,1,1,1,1,1,1,1,1,1,1,1,1,1,1,1,1,1,1,1,1,1,1,1,1,1,1,1,1,1,1,2,2,2,2,2,2,2,1,1,1,1,1,1,1,1,1,1,5,5,7,7,7,2,2,1,1,1,1,1,1,1,1,1,5,5,8,8,8,8,7,2,2,1,1,1,1,1,1,1,1,5,8,8,8,8,8,7,3,2,1,1,1,1,1,1,1,1,5,5,8,8,8,8,7,2,2,1,1,1,1,1,1,1,1,5,5,5,7,7,7,2,2,1,1,1,1,1,1,1,1,1,1,5,5,2,2,2,2,2,1,1,1,1,1,1,1,1,1,1,1,1,1,1,1,1,1,1,1,1,1,1,1,1,1,1,1,1,1,1,1,1,1,1,1,1,1,1,1,1,1,1,1,1,1,1,1,1,1,1,1,1,1,1,1,1,1,1,1,1,1,1,1,1,1,1,1,1,1,1,1,1,1</Field>
        </Group>
    </Page>
    <Page Name="BlackLevel">
        <Group Name="BlackLevelValue">
			<Field Name="OpType">1</Field>
            <Field Name="BlackLevel[0]">64</Field>
            <Field Name="BlackLevel[1]">64</Field>
            <Field Name="BlackLevel[2]">64</Field>
            <Field Name="BlackLevel[3]">64</Field>
        </Group>
    </Page>
    <Page Name="DRC">
        <Group Name="DRC">
		    <Field Name="Enable">1</Field>
            <Field Name="CurveSelect">0</Field>
			<Field Name="LocalMixingBrightMax">24</Field>
			<Field Name="LocalMixingBrightMin">18</Field>
			<Field Name="LocalMixingBrightThr">96</Field>
			<Field Name="LocalMixingDarkMax">38</Field>
			<Field Name="LocalMixingDarkMin">32</Field>
			<Field Name="LocalMixingDarkThr">200</Field>
			<Field Name="BrightGainLmt">12</Field>
			<Field Name="BrightGainLmtStep">10</Field>
			<Field Name="DarkGainLmtY">88</Field>
			<Field Name="DarkGainLmtC">0</Field>
			<Field Name="ContrastControl">10</Field>
			<Field Name="DetailAdjustFactor">15</Field>
			<Field Name="DRCAsymmetryCurveAsymmetry">8</Field>
			<Field Name="DRCAsymmetryCurveSecondPole">158</Field>
			<Field Name="DRCAsymmetryCurveStretch">50</Field>
			<Field Name="DRCAsymmetryCurveCompress">110</Field>
			<Field Name="DRCOpType">1</Field>
			<Field Name="DRCManualStrength">468</Field>
			<Field Name="DRCAutoStr">512</Field>
			<Field Name="DRCAutoStrMin">0</Field>
			<Field Name="DRCAutoStrMax">512</Field>
			<Field Name="DRCToneMappingValue">4095,5995,8191,11583,15287,19483,23987,27548,30548,31999,32988,33896,34721,35112,35481,35830,36162,36326,36483,36640,36795,36949,37103,37259,37419,37499,37580,37666,37751,37797,37921,38016,38116,38215,38317,38423,38533,38649,38760,38896,39029,39098,39168,39238,39315,39393,39469,39553,39635,39723,39777,39903,39995,40093,40193,40296,40402,40511,40624,40740,40850,40979,41111,41244,41380,41512,41670,41820,41977,42138,42305,42477,42655,42746,42840,42935,43028,43119,43195,43326,43433,43538,43644,43753,43863,43976,44090,44205,44324,44444,44567,44692,44818,44947,45077,45208,45348,45487,45627,45771,45917,46065,46216,46368,46526,46685,46846,47012,47174,47339,47525,47702,47882,48064,48251,48440,48631,48832,49032,49232,49414,49656,49872,50090,50314,50542,50773,51007,51237,51486,51742,51994,52253,52516,52783,53054,53332,53472,53610,53754,53897,54049,54195,54344,54494,54645,54797,54952,55107,55263,55421,55581,55737,55906,55985,56227,56403,56572,56743,56914,57088,57263,57440,57617,57799,57980,58163,58349,58533,58721,58915,59107,59301,59496,59693,59893,60093,60298,60478,60702,60919,61129,61293,61557,61774,61993,62213,62437,62662,62889,63109,63349,63580,63819,64057,64298,64541,64786,65034,65283</Field>
        </Group>
    </Page>
    <Page Name="3DNR_X">
		<Data>64,64,64,64,0,0,0,64,64,64,64,0,0,0,64,64,64,64,0,0,0,110,80,64,64,0,0,0,110,90,64,64,0,0,0,4,31,2,0,16,16,4,4,0,0,7,0,11,12,0,53,0,108,58,0,108,53,0,108,38,2,6,1,26,0,47,4,0,0,34,0,0,0,0,0,0,0,0,0,0,0,0,0,0,0,0,0,0,0,0,0,0,0,0,0,0,0,0,0,0,0,0,0,0,0,0,0,0,0,0,0,0,0,0,0,0,0,0,0,0,0,0,0,0,0,0,0,0,0,0,0,0,0,0,0,4,31,2,0,0,0,4,3,0,0,12,0,11,12,0,58,0,128,83,0,128,58,0,128,48,2,6,1,32,0,40,4,0,0,30,0,0,0,0,0,0,0,0,0,0,0,0,0,0,0,0,0,0,0,0,0,0,0,0,0,0,0,0,0,0,0,0,0,0,0,0,0,0,0,0,0,0,0,0,0,0,0,0,0,0,0,0,0,0,0,0,0,0,0,0,0,0,0,0,0,4,26,2,0,0,0,4,3,0,0,12,0,11,12,0,60,0,128,83,0,128,60,0,128,36,2,6,1,28,0,48,4,0,0,36,0,0,0,0,0,0,0,0,0,0,0,0,0,0,0,0,0,0,0,0,0,0,0,0,0,0,0,0,0,0,0,0,0,0,0,0,0,0,0,0,0,0,0,0,0,0,0,0,0,0,0,0,0,0,0,0,0,0,0,0,0,0,0,0,0,1,26,5,0,0,0,4,3,22,22,0,0,12,13,0,68,0,128,69,0,128,50,0,128,44,2,6,1,31,0,51,4,0,0,43,0,0,0,0,0,0,0,0,0,0,0,0,0,0,0,0,0,0,0,0,0,0,0,0,0,0,0,0,0,0,0,0,0,0,0,0,0,0,0,0,0,0,0,0,0,0,0,0,0,0,0,0,0,0,0,0,0,0,0,0,0,0,0,0,0,1,31,5,0,0,0,4,3,22,22,22,0,12,14,0,80,0,0,80,0,0,80,0,0,40,6,6,0,32,0,48,4,0,0,25,0,0,0,0,0,0,0,0,0,0,0,0,0,0,0,0,0,0,0,0,0,0,0,0,0,0,0,0,0,0,0,0,0,0,0,0,0,0,0,0,0,0,0,0,0,0,0,0,0,0,0,0,0,0,0,0,0,0,0,0,0,0,0,0,0,0,1,1,2,0,0,2,2,2,0,0,0,97,2,3,87,0,360,0,320,0,12,3,4,9,1,0,0,0,1,1,2,0,0,0,0,0,0,0,0,373,3,3,356,0,180,0,137,0,12,3,5,5,0,0,0,2,0,2,0,0,0,0,31,0,0,0,0,8,1,2,0,4,0,0,0,0,0,0,0,0,0,0,0,12,0,1,0,9,0,2,13,0,2,0,31,0,0,31,0,4,1,8,4,8,4,0,0,1,1,16,8,16,8,0,0,0,0,1,0,11,0,2,0,0,0,0,31,0,0,0,0,1,1,16,8,16,8,0,0,0,0,16,8,16,0,8,0,0,0,0,0,247,27,0,35,15,0</Data>
    </Page>
    <Page Name="Gamma">
        <Data>0,13,27,40,53,67,80,94,107,121,134,148,162,175,189,203,216,230,244,258,272,285,299,313,327,340,354,368,382,395,409,423,436,450,464,477,491,504,518,531,544,558,571,584,597,610,624,637,649,662,675,688,701,713,726,738,750,763,775,787,799,811,823,834,846,858,869,880,892,903,914,925,936,947,958,969,980,991,1002,1012,1023,1033,1044,1054,1065,1075,1085,1096,1106,1116,1126,1136,1146,1156,1166,1176,1185,1195,1205,1215,1224,1234,1243,1253,1262,1272,1281,1290,1300,1309,1318,1327,1337,1346,1355,1364,1373,1382,1391,1400,1409,1418,1426,1435,1444,1453,1462,1470,1479,1488,1496,1505,1513,1522,1530,1539,1547,1555,1564,1572,1580,1588,1596,1604,1612,1620,1628,1636,1644,1652,1660,1667,1675,1683,1690,1698,1706,1713,1721,1728,1735,1743,1750,1757,1765,1772,1779,1786,1794,1801,1808,1815,1822,1829,1836,1843,1850,1857,1864,1870,1877,1884,1891,1898,1904,1911,1918,1924,1931,1937,1944,1951,1957,1964,1970,1976,1983,1989,1995,2002,2008,2014,2020,2027,2033,2039,2045,2051,2057,2063,2069,2075,2080,2086,2092,2098,2104,2109,2115,2121,2126,2132,2137,2143,2148,2154,2159,2165,2170,2176,2181,2186,2192,2197,2202,2207,2213,2218,2223,2228,2233,2238,2243,2248,2253,2258,2263,2268,2273,2278,2283,2288,2293,2298,2302,2307,2312,2317,2321,2326,2331,2335,2340,2344,2349,2353,2358,2362,2367,2371,2375,2379,2384,2388,2392,2396,2400,2404,2409,2413,2417,2421,2425,2429,2433,2436,2440,2444,2448,2452,2456,2460,2463,2467,2471,2475,2479,2482,2486,2490,2493,2497,2501,2505,2508,2512,2516,2519,2523,2527,2530,2534,2538,2541,2545,2549,2552,2556,2560,2563,2567,2571,2574,2578,2582,2585,2589,2592,2596,2599,2603,2607,2610,2614,2617,2621,2624,2628,2631,2635,2638,2642,2645,2649,2652,2655,2659,2662,2666,2669,2672,2676,2679,2683,2686,2689,2693,2696,2699,2703,2706,2709,2713,2716,2719,2723,2726,2729,2732,2736,2739,2742,2745,2749,2752,2755,2758,2761,2765,2768,2771,2774,2777,2780,2784,2787,2790,2793,2796,2799,2802,2806,2809,2812,2815,2818,2821,2824,2827,2830,2833,2836,2839,2842,2845,2848,2851,2854,2857,2860,2863,2866,2869,2872,2875,2878,2881,2884,2887,2890,2893,2896,2899,2902,2905,2908,2911,2913,2916,2919,2922,2925,2928,2931,2934,2936,2939,2942,2945,2948,2951,2953,2956,2959,2962,2965,2967,2970,2973,2976,2979,2981,2984,2987,2990,2992,2995,2998,3001,3003,3006,3009,3012,3014,3017,3020,3022,3025,3028,3031,3033,3036,3039,3041,3044,3047,3049,3052,3054,3057,3060,3062,3065,3068,3070,3073,3076,3078,3081,3083,3086,3088,3091,3094,3096,3099,3101,3104,3107,3109,3112,3114,3117,3119,3122,3124,3127,3129,3132,3134,3137,3139,3142,3144,3147,3149,3152,3154,3157,3159,3162,3164,3167,3169,3172,3174,3177,3179,3182,3184,3186,3189,3191,3194,3196,3199,3201,3203,3206,3208,3211,3213,3215,3218,3220,3223,3225,3227,3230,3232,3234,3237,3239,3241,3244,3246,3248,3251,3253,3256,3258,3260,3262,3265,3267,3269,3272,3274,3276,3279,3281,3283,3286,3288,3290,3292,3295,3297,3299,3302,3304,3306,3308,3311,3313,3315,3317,3320,3322,3324,3326,3329,3331,3333,3335,3337,3340,3342,3344,3346,3348,3351,3353,3355,3357,3359,3362,3364,3366,3368,3370,3373,3375,3377,3379,3381,3383,3386,3388,3390,3392,3394,3396,3398,3401,3403,3405,3407,3409,3411,3413,3415,3418,3420,3422,3424,3426,3428,3430,3432,3434,3437,3439,3441,3443,3445,3447,3449,3451,3453,3455,3457,3459,3461,3463,3466,3468,3470,3472,3474,3476,3478,3480,3482,3484,3486,3488,3490,3492,3494,3496,3498,3500,3502,3504,3506,3508,3510,3512,3514,3516,3518,3520,3522,3524,3526,3528,3530,3532,3534,3536,3538,3540,3542,3544,3546,3548,3550,3552,3554,3556,3558,3559,3561,3563,3565,3567,3569,3571,3573,3575,3577,3579,3581,3583,3585,3587,3588,3590,3592,3594,3596,3598,3600,3602,3604,3606,3607,3609,3611,3613,3615,3617,3619,3621,3622,3624,3626,3628,3630,3632,3634,3636,3637,3639,3641,3643,3645,3647,3649,3650,3652,3654,3656,3658,3660,3661,3663,3665,3667,3669,3671,3672,3674,3676,3678,3680,3681,3683,3685,3687,3689,3690,3692,3694,3696,3698,3699,3701,3703,3705,3707,3708,3710,3712,3714,3716,3717,3719,3721,3723,3724,3726,3728,3730,3731,3733,3735,3737,3738,3740,3742,3744,3745,3747,3749,3751,3752,3754,3756,3758,3759,3761,3763,3765,3766,3768,3770,3771,3773,3775,3777,3778,3780,3782,3784,3785,3787,3789,3790,3792,3794,3795,3797,3799,3801,3802,3804,3806,3807,3809,3811,3812,3814,3816,3817,3819,3821,3822,3824,3826,3827,3829,3831,3832,3834,3836,3837,3839,3841,3842,3844,3846,3847,3849,3851,3852,3854,3856,3857,3859,3860,3862,3864,3865,3867,3869,3870,3872,3873,3875,3877,3878,3880,3882,3883,3885,3886,3888,3890,3891,3893,3894,3896,3898,3899,3901,3902,3904,3906,3907,3909,3910,3912,3914,3915,3917,3918,3920,3922,3923,3925,3926,3928,3929,3931,3933,3934,3936,3937,3939,3940,3942,3944,3945,3947,3948,3950,3951,3953,3954,3956,3958,3959,3961,3962,3964,3965,3967,3968,3970,3971,3973,3975,3976,3978,3979,3981,3982,3984,3985,3987,3988,3990,3991,3993,3994,3996,3997,3999,4000,4002,4003,4005,4006,4008,4010,4011,4013,4014,4016,4017,4019,4020,4022,4023,4025,4026,4028,4029,4030,4032,4033,4035,4036,4038,4039,4041,4042,4044,4045,4047,4048,4050,4051,4053,4054,4056,4057,4059,4060,4061,4063,4064,4066,4067,4069,4070,4072,4073,4075,4076,4078,4079,4080,4082,4083,4085,4086,4088,4089,4091,4092,4093,4095</Data>
    </Page>
    <Page Name="DEHAZE">
        <Group Name="DEHAZE Attr">
		    <Field Name="bEnable">1</Field>
            <Field Name="bUserLutEnable">1</Field>
			<Field Name="au8DehazeLut">145,146,147,148,150,151,152,154,155,156,158,159,160,162,163,165,166,167,169,170,172,173,174,176,177,179,180,181,183,184,186,187,188,190,191,192,194,195,196,198,199,200,202,203,204,205,206,208,209,210,211,212,214,215,216,217,218,219,220,221,222,223,224,225,226,226,227,228,229,230,230,231,232,233,233,234,235,235,236,236,237,238,238,239,239,240,240,241,241,242,242,243,243,244,244,245,245,245,246,246,247,247,247,248,248,248,249,249,249,250,250,250,251,251,251,251,252,252,252,252,253,253,253,253,254,254,254,254,255,255,255,255,255,255,255,255,255,255,255,255,255,255,255,255,255,255,255,255,255,255,255,255,255,255,255,255,255,255,255,255,255,255,255,255,255,255,255,255,255,255,255,255,255,255,255,255,255,255,255,255,255,255,255,255,255,255,255,255,255,255,255,255,255,255,255,255,255,255,255,255,255,255,255,255,255,255,255,255,255,255,255,255,255,255,255,255,255,255,255,255,255,255,255,255,255,255,255,255,255,255,255,255,255,255,255,255,255,255,255,255,255,255,255,255,255,255,255,255,255,255,255,255,255,255,255,255</Field>
			<Field Name="enOpType">1</Field>
			<Field Name="stManual.u8strength">145</Field>
			<Field Name="stAuto.u8strength">120</Field>
        </Group>
    </Page>
	<Page Name="CA">
        <Group Name="CaAttr">
            <Field Name="bEnable">1</Field>
            <Field Name="ISORatio">1024,1024,1100,1100,1024,1100,1050,1000,1000,1000,900,800,800,800,800,800</Field>
			<Field Name="YRatioLut">516,525,534,544,554,563,573,583,594,604,614,624,634,644,654,664,674,684,694,704,713,723,732,741,750,758,766,775,782,790,797,804,811,817,823,828,834,839,844,848,853,857,861,865,868,872,875,878,881,884,887,890,892,895,898,900,903,905,908,910,913,915,918,921,924,926,929,932,935,937,940,943,945,948,950,952,955,957,959,961,964,966,968,970,972,974,976,978,979,981,983,985,987,988,990,992,993,994,995,996,997,998,998,999,1000,1001,1002,1002,1003,1004,1005,1006,1006,1007,1008,1009,1010,1011,1012,1013,1014,1015,1016,1018,1019,1020,1022,1024</Field>
        </Group>
    </Page>
</Table>
